file_system/__init__.py
file_system/file.py
emo_file_system-0.0.6.dist-info/LICENSE
emo_file_system-0.0.6.dist-info/METADATA
emo_file_system-0.0.6.dist-info/WHEEL
emo_file_system-0.0.6.dist-info/top_level.txt
emo_file_system-0.0.6.dist-info/RECORD
