Metadata-Version: 2.1
Name: emo_file_system
Version: 0.0.6
Summary: Dosya işlemlerini yöneten modül
Home-page: https://github.com/erenmustafaozdal/file-system
Author: Eren Mustafa Özdal
Author-email: eren.060737@gmail.com
License: MIT
Requires-Python: >=3.11
License-File: LICENSE
